webdocs/__init__.py
webdocs/exceptions.py
webdocs/openapi_doc.py
webdocs/openapi_v3_schema.json
webdocs/utils.py
webdocs/django/__init__.py
webdocs/django/apps.py
webdocs/django/openapi_doc.py
webdocs/django/management/__init__.py
webdocs/django/management/commands/__init__.py
webdocs/django/management/commands/generate_api_doc.py
webdocs/django/management/commands/preview_api_doc.py
webdocs/preview/__init__.py
webdocs/preview/flask_app.py
webdocs/preview/templates/swagger-editor.html
webdocs/preview/templates/swagger-ui.html
webdocs-1.0.1.dist-info/METADATA
webdocs-1.0.1.dist-info/WHEEL
webdocs-1.0.1.dist-info/top_level.txt
webdocs-1.0.1.dist-info/RECORD
